GCMicrolensing/TestML.py
GCMicrolensing/__init__.py
GCMicrolensing/models.py
GCMicrolensing/triplelens/Functions4Images.ipynb
GCMicrolensing/triplelens/LICENSE.md
GCMicrolensing/triplelens/Makefile
GCMicrolensing/triplelens/README.md
GCMicrolensing/triplelens/TripleLensing.cpython-312-x86_64-linux-gnu.so
GCMicrolensing/triplelens/__init__.py
GCMicrolensing/triplelens/setup.cfg
GCMicrolensing/triplelens/setup.py
GCMicrolensing/triplelens/bin/testtriple
GCMicrolensing/triplelens/data/allImages.dat
GCMicrolensing/triplelens/data/allTracks.dat
GCMicrolensing/triplelens/data/allTracks_before.dat
GCMicrolensing/triplelens/data/caustics.dat
GCMicrolensing/triplelens/data/critical_curves.dat
GCMicrolensing/triplelens/data/ftrilkv_adaptive_rs5e-3.dat
GCMicrolensing/triplelens/data/fulltrilkv_rs5e-3.dat
GCMicrolensing/triplelens/data/lens_system.dat
GCMicrolensing/triplelens/data/lens_system_triple.dat
GCMicrolensing/triplelens/data/limblkv.dat
GCMicrolensing/triplelens/data/magmap0.05.dat
GCMicrolensing/triplelens/data/pureImgPoints.dat
GCMicrolensing/triplelens/data/pureImgPoints_centre.dat
GCMicrolensing/triplelens/data/pureImgPoints_falseimg.dat
GCMicrolensing/triplelens/data/unilkv.dat
GCMicrolensing/triplelens/doc/connected_track_eg.gif
GCMicrolensing/triplelens/doc/connected_track_eg2.gif
GCMicrolensing/triplelens/doc/demolkvs.npz
GCMicrolensing/triplelens/doc/demolkvs_0.npz
GCMicrolensing/triplelens/doc/lkvs.png
GCMicrolensing/triplelens/doc/ob120026-lkv.png
GCMicrolensing/triplelens/doc/top_lkv.gif
GCMicrolensing/triplelens/doc/top_lkv.mp4
GCMicrolensing/triplelens/pymodule/python_bindings.cpp
GCMicrolensing/triplelens/src/TripleLensingLibrary.cpp
GCMicrolensing/triplelens/src/TripleLensingLibrary.h
GCMicrolensing/triplelens/src/VBBinaryLensingLibrary.cpp
GCMicrolensing/triplelens/src/VBBinaryLensingLibrary.h
GCMicrolensing/triplelens/test/plotcaus.py
GCMicrolensing/triplelens/test/plotlkv.py
GCMicrolensing/triplelens/test/plotlkvadap.py
gcmicrolensing-0.1.0.dist-info/licenses/LICENSE
gcmicrolensing-0.1.0.dist-info/METADATA
gcmicrolensing-0.1.0.dist-info/WHEEL
gcmicrolensing-0.1.0.dist-info/top_level.txt
gcmicrolensing-0.1.0.dist-info/RECORD
